{"assembly_form_date-picker.md":"5c6114ad","assembly_form_on.md":"2cf14d5a","assembly_advanced_customform.md":"79eb31c6","assembly_form_slot.md":"2081c847","assembly_form_rules-plus.md":"9d3d6311","assembly_form_deprecated.md":"66b6dbb8","assembly_form_get-component-by-id.md":"8171a973","assembly_form_radio-group.md":"52598721","assembly_form_checkbox-group.md":"7b880d40","assembly_form_set-options.md":"6b9cb6b1","assembly_advanced_customformroules.md":"137f423d","index.md":"f5c0a7b4","assembly_form_disabled.md":"c70d39d1","assembly_form_remote.md":"3173ea21","assembly_form_content.md":"7e49928d","assembly_form_rules.md":"2773a393","assembly_form_el.md":"e7c42ee4","assembly_form_slot-label.md":"5187c376","guide_table.md":"4a405abc","assembly_form_hidden.md":"00926d42","assembly_form_get-form-value.md":"20d141c0","assembly_form_update-form.md":"7ab65351","assembly_form_v-model.md":"f8b8f80f","assembly_form_basic.md":"04efb572","assembly_form_readonly.md":"e6d69789","assembly_form_next-tick.md":"4643f5b6","assembly_form_value-format.md":"6904d86f","assembly_advanced_upload.md":"26cfdf6f","assembly_table_table.md":"88379d01","guide_form.md":"c20cffa1","assembly_advanced_uploadfile.md":"03238925"}
